asciimath_printer.py
latex2sympy2.py
gen/PSLexer.py
gen/PSListener.py
gen/PSParser.py
gen/__init__.py
latex2sympy/__init__.py
latex2sympy/__main__.py
latex2sympy/latex2sympy.py
latex2sympy/gen/PSLexer.py
latex2sympy/gen/PSListener.py
latex2sympy/gen/PSParser.py
latex2sympy/gen/__init__.py
tests/__init__.py
tests/abs_test.py
tests/all_bad_test.py
tests/all_good_test.py
tests/atom_expr_test.py
tests/binomial_test.py
tests/ceil_test.py
tests/complex_test.py
tests/context.py
tests/exp_test.py
tests/floor_test.py
tests/gcd_test.py
tests/greek_test.py
tests/grouping_test.py
tests/lcm_test.py
tests/left_right_cdot_test.py
tests/linalg_test.py
tests/max_test.py
tests/min_test.py
tests/mod_test.py
tests/overline_test.py
tests/pi_test.py
tests/trig_test.py
tests/variable_test.py
sympy_latex_parser-1.9.0.dist-info/LICENSE.txt
sympy_latex_parser-1.9.0.dist-info/METADATA
sympy_latex_parser-1.9.0.dist-info/WHEEL
sympy_latex_parser-1.9.0.dist-info/top_level.txt
sympy_latex_parser-1.9.0.dist-info/RECORD
