Metadata-Version: 2.1
Name: sympy-latex-parser
Version: 1.9.0
Summary: Convert latex to sympy with ANTLR and support Matrix, Linear Algebra and CAS functions.
Home-page: https://github.com/niklaskorz/latex2sympy/
Author: Niklas Korz
Author-email: contact@korz.dev
License: MIT
Classifier: Development Status :: 4 - Beta
Classifier: Intended Audience :: Developers
Classifier: Intended Audience :: Education
Classifier: Intended Audience :: Science/Research
Classifier: License :: OSI Approved :: MIT License
Classifier: Topic :: Education
Classifier: Topic :: Scientific/Engineering :: Mathematics
Classifier: Topic :: Software Development :: Compilers
Classifier: Topic :: Text Processing :: Markup :: LaTeX
Classifier: Topic :: Text Processing :: Markup :: Markdown
Classifier: Programming Language :: Python :: 3
Classifier: Programming Language :: Python :: 3.3
Classifier: Programming Language :: Python :: 3.4
Classifier: Programming Language :: Python :: 3.5
Classifier: Programming Language :: Python :: 3.6
Classifier: Programming Language :: Python :: 3.7
Classifier: Programming Language :: Python :: 3.8
License-File: LICENSE.txt
Requires-Dist: sympy >=1.12
Requires-Dist: antlr4-python3-runtime ==4.13.1
